kata/__init__.py
kata/__main__.py
kata/_version.py
kata/cli/__init__.py
kata/cli/app.py
kata/cli/commands/__init__.py
kata/core/__init__.py
kata/core/config.py
kata/core/models.py
kata/core/settings.py
kata/core/templates.py
kata/services/__init__.py
kata/services/loop.py
kata/services/registry.py
kata/services/routine.py
kata/services/sessions.py
kata/tui/__init__.py
kata/tui/app.py
kata/tui/themes.py
kata/tui/screens/__init__.py
kata/tui/screens/context_menu.py
kata/tui/screens/search.py
kata/tui/screens/settings.py
kata/tui/screens/wizard.py
kata/tui/widgets/__init__.py
kata/tui/widgets/layout.py
kata/tui/widgets/preview.py
kata/tui/widgets/recents.py
kata/tui/widgets/status.py
kata/tui/widgets/tree.py
kata/utils/__init__.py
kata/utils/detection.py
kata/utils/fzf.py
kata/utils/git.py
kata/utils/paths.py
kata/utils/scanner.py
kata/utils/zoxide.py
kata_workspace-0.2.2.dist-info/METADATA
kata_workspace-0.2.2.dist-info/WHEEL
kata_workspace-0.2.2.dist-info/entry_points.txt
kata_workspace-0.2.2.dist-info/RECORD
