Metadata-Version: 2.4
Name: kata-workspace
Version: 0.2.2
Summary: Terminal-centric workspace orchestrator for tmux power users
Project-URL: Homepage, https://github.com/kata-workspace/kata
Project-URL: Documentation, https://github.com/kata-workspace/kata#readme
Project-URL: Repository, https://github.com/kata-workspace/kata
Project-URL: Issues, https://github.com/kata-workspace/kata/issues
Author: Kata Contributors
License: MIT
Keywords: cli,orchestrator,terminal,tmux,tui,workspace
Classifier: Development Status :: 3 - Alpha
Classifier: Environment :: Console
Classifier: Intended Audience :: Developers
Classifier: License :: OSI Approved :: MIT License
Classifier: Operating System :: MacOS
Classifier: Operating System :: POSIX
Classifier: Programming Language :: Python :: 3
Classifier: Programming Language :: Python :: 3.10
Classifier: Programming Language :: Python :: 3.11
Classifier: Programming Language :: Python :: 3.12
Classifier: Topic :: Software Development :: User Interfaces
Classifier: Topic :: Terminals :: Terminal Emulators/X Terminals
Requires-Python: >=3.10
Requires-Dist: libtmux>=0.37.0
Requires-Dist: pyyaml>=6.0.0
Requires-Dist: rich>=13.0.0
Requires-Dist: textual>=0.47.0
Requires-Dist: tmuxp>=1.47.0
Requires-Dist: typer>=0.9.0
Provides-Extra: dev
Requires-Dist: mypy>=1.8.0; extra == 'dev'
Requires-Dist: pre-commit>=3.6.0; extra == 'dev'
Requires-Dist: pytest-asyncio>=0.23.0; extra == 'dev'
Requires-Dist: pytest-cov>=4.0.0; extra == 'dev'
Requires-Dist: pytest>=8.0.0; extra == 'dev'
Requires-Dist: ruff>=0.3.0; extra == 'dev'
